pystone.py
setup.py
micropython_pystone.egg-info/PKG-INFO
micropython_pystone.egg-info/SOURCES.txt
micropython_pystone.egg-info/dependency_links.txt
micropython_pystone.egg-info/top_level.txt